setup.py
jija/__init__.py
jija/app.py
jija/apps.py
jija/collector.py
jija/command.py
jija/exceptions.py
jija/middleware.py
jija/reloader.py
jija/response.py
jija/router.py
jija/views.py
jija.egg-info/PKG-INFO
jija.egg-info/SOURCES.txt
jija.egg-info/dependency_links.txt
jija.egg-info/not-zip-safe
jija.egg-info/requires.txt
jija.egg-info/top_level.txt
jija/base_app/app.py
jija/base_app/middlewares.py
jija/base_app/commands/migrate.py
jija/base_app/commands/run.py
jija/base_app/commands/runprocess.py
jija/base_app/commands/update.py
jija/config/__init__.py
jija/config/base.py
jija/config/dev.py
jija/config/drivers.py
jija/config/network.py
jija/config/structute.py
jija/contrib/auth/config.py
jija/contrib/jija_orm/driver.py
jija/contrib/swagger/driver.py
jija/contrib/swagger/processor.py
jija/contrib/swagger/views.py
jija/drivers/__init__.py
jija/drivers/base.py
jija/drivers/database.py
jija/drivers/docs.py
jija/serializers/__init__.py
jija/serializers/exceptions.py
jija/serializers/fields.py
jija/serializers/serializer.py
jija/serializers/validators.py