Metadata-Version: 2.1
Name: jija
Version: 0.3.1
Summary: Async framework for web development with graceful collector
Home-page: https://gitlab.com/by_dezz/jija/
Author: Kain
Author-email: kainedezz.2000@gmail.com
License: UNKNOWN
Platform: UNKNOWN
